CFrontClasses.py
CfnCustomCFrontDistro.py
CfnCustomCFrontDistro-0.0.1.dist-info/METADATA
CfnCustomCFrontDistro-0.0.1.dist-info/WHEEL
CfnCustomCFrontDistro-0.0.1.dist-info/top_level.txt
CfnCustomCFrontDistro-0.0.1.dist-info/RECORD
