Metadata-Version: 2.1
Name: CfnCustomCFrontDistro
Version: 0.0.1
Summary: AWS cloudformation CloudFront Distributions with OriginGroups support
Home-page: https://github.com/karmafeast/CfnCustomCFrontDistro
Author: karmafeast
Author-email: karmafeast@gmail.com
License: UNKNOWN
Platform: UNKNOWN
Classifier: Programming Language :: Python :: 3
Classifier: License :: OSI Approved :: MIT License
Classifier: Operating System :: OS Independent
Requires-Python: >=3.7
Requires-Dist: boto3 (>=1.9.189)
Requires-Dist: botocore (>=1.12.189)
Requires-Dist: crhelper (>=2.0.4)
Requires-Dist: pytest (>=5.0.1)
Requires-Dist: str2bool (>=1.1)
